kakao_response_formatter/__init__.py
kakao_response_formatter/formatter.py
kakao_response_formatter-0.0.1.dist-info/METADATA
kakao_response_formatter-0.0.1.dist-info/WHEEL
kakao_response_formatter-0.0.1.dist-info/top_level.txt
kakao_response_formatter-0.0.1.dist-info/RECORD
